scriptperf/__init__.py
scriptperf/cli.py
scriptperf/monitor.py
scriptperf/plotter.py
scriptperf-0.0.3.dist-info/licenses/LICENSE.txt
scriptperf-0.0.3.dist-info/METADATA
scriptperf-0.0.3.dist-info/WHEEL
scriptperf-0.0.3.dist-info/entry_points.txt
scriptperf-0.0.3.dist-info/top_level.txt
scriptperf-0.0.3.dist-info/RECORD
