Metadata-Version: 2.4
Name: scriptperf
Version: 0.0.3
Summary: Run Python scripts with performance monitoring (CPU and memory usage tracking)
Home-page: https://github.com/all-for-freedom/scriptperf
Author: all-for-freedom
Author-email: yangshen@hunnu.edu.cn
License: MIT
Project-URL: Source, https://github.com/all-for-freedom/scriptperf
Project-URL: Changelog, https://github.com/all-for-freedom/scriptperf/blob/main/CHANGELOG.rst
Project-URL: Tracker, https://github.com/all-for-freedom/scriptperf/issues
Platform: any
Classifier: Development Status :: 4 - Beta
Classifier: Programming Language :: Python
License-File: LICENSE.txt
Requires-Dist: psutil>=5.9.0
Requires-Dist: matplotlib>=3.5.0
Requires-Dist: importlib-metadata; python_version < "3.8"
Provides-Extra: testing
Requires-Dist: setuptools; extra == "testing"
Requires-Dist: pytest; extra == "testing"
Requires-Dist: pytest-cov; extra == "testing"
Dynamic: license-file
